squad/__init__.py
squad/admin.py
squad/celery.py
squad/compat.py
squad/container_settings.py
squad/http.py
squad/jinja2.py
squad/mail.py
squad/manage.py
squad/settings.py
squad/socialaccount.py
squad/urls.py
squad/version.py
squad/wsgi.py
squad/api/__init__.py
squad/api/apps.py
squad/api/ci.py
squad/api/data.py
squad/api/filters.py
squad/api/prometheus.py
squad/api/rest.py
squad/api/urls.py
squad/api/utils.py
squad/api/views.py
squad/ci/__init__.py
squad/ci/admin.py
squad/ci/apps.py
squad/ci/exceptions.py
squad/ci/models.py
squad/ci/tasks.py
squad/ci/utils.py
squad/ci/backend/__init__.py
squad/ci/backend/fake.py
squad/ci/backend/lava.py
squad/ci/backend/null.py
squad/ci/backend/tuxsuite.py
squad/ci/management/__init__.py
squad/ci/management/commands/__init__.py
squad/ci/management/commands/create_tuxsuite_boot_tests.py
squad/ci/management/commands/listen.py
squad/ci/management/commands/testfetch.py
squad/ci/migrations/0001_initial.py
squad/ci/migrations/0002_auto_20170406_1252.py
squad/ci/migrations/0003_backend_name.py
squad/ci/migrations/0004_testjob_failure.py
squad/ci/migrations/0005_remove_listener_data.py
squad/ci/migrations/0006_simplify_backend_loading.py
squad/ci/migrations/0007_auto_20170517_1736.py
squad/ci/migrations/0008_testjob_testrun.py
squad/ci/migrations/0009_slug_pattern.py
squad/ci/migrations/0010_testjob_can_resubmit.py
squad/ci/migrations/0011_testjob_resubmitted_count.py
squad/ci/migrations/0012_testjob_build.py
squad/ci/migrations/0013_testjob_name.py
squad/ci/migrations/0014_testjob_target_build.py
squad/ci/migrations/0015_testjob_populate_target_build.py
squad/ci/migrations/0016_backend_max_fetch_attempts.py
squad/ci/migrations/0017_testjob_fetch_attempts.py
squad/ci/migrations/0018_testjob_dates.py
squad/ci/migrations/0019_add_fake_backend.py
squad/ci/migrations/0020_backend_settings_field.py
squad/ci/migrations/0021_testjob_parent_job.py
squad/ci/migrations/0022_backend_poll_enabled.py
squad/ci/migrations/0023_remove_testjob_build.py
squad-1.98.dist-info/licenses/COPYING
squad-1.98.dist-info/METADATA
squad-1.98.dist-info/WHEEL
squad-1.98.dist-info/entry_points.txt
squad-1.98.dist-info/top_level.txt
squad-1.98.dist-info/RECORD
