Metadata-Version: 2.4
Name: squad
Version: 1.98
Summary: Software Quality Dashboard
Home-page: https://gitlab.com/Linaro/squad/squad
Author: Antonio Terceiro
Author-email: antonio.terceiro@linaro.org
License: GPLv3+
Platform: any
License-File: COPYING
Requires-Dist: aiohttp
Requires-Dist: celery
Requires-Dist: cryptography
Requires-Dist: django_crispy_forms==1.14.0
Requires-Dist: Django<5,>=3
Requires-Dist: django-allauth
Requires-Dist: django-bootstrap3
Requires-Dist: django-celery-results
Requires-Dist: django-cors-headers
Requires-Dist: django-debug-toolbar
Requires-Dist: django-simple-history>3.0
Requires-Dist: django_filter>=2.0
Requires-Dist: djangorestframework>=3.9.2
Requires-Dist: djangorestframework-filters>=1.0.0.dev0
Requires-Dist: drf-extensions
Requires-Dist: future
Requires-Dist: gunicorn
Requires-Dist: importlib-metadata>3
Requires-Dist: Jinja2==3.0.3
Requires-Dist: Markdown
Requires-Dist: msgpack>=0.5.0
Requires-Dist: psycopg2-binary
Requires-Dist: python_dateutil
Requires-Dist: PyYAML>=5.1
Requires-Dist: PyJWT
Requires-Dist: pyzmq
Requires-Dist: requests
Requires-Dist: setuptools
Requires-Dist: sqlparse
Requires-Dist: svgwrite
Requires-Dist: whitenoise
Requires-Dist: pytz
Provides-Extra: postgres
Requires-Dist: psycopg2-binary; extra == "postgres"
Dynamic: author
Dynamic: author-email
Dynamic: description
Dynamic: home-page
Dynamic: license
Dynamic: license-file
Dynamic: platform
Dynamic: provides-extra
Dynamic: requires-dist
Dynamic: summary
